{
  "pages": [
    {
      "slug": ["espresso-premium"],
      "template": "product-grid",
      "data_source": "supabase",
      "category_filter": "espresso-premium",
      "seo": {
        "title": "Machines Espresso Premium | MUTHOS",
        "description": "Verdict technique sur les systèmes d'extraction de précision."
      }
    },
    {
      "slug": ["comparatif", "lelit-vs-rocket"],
      "template": "comparison",
      "comparison_models": ["Bianca V3", "Cinquantotto"], 
      "seo": {
        "title": "Lelit Bianca vs Rocket R Cinquantotto | MUTHOS",
        "description": "Duel thermodynamique entre deux icônes du groupe E61."
      }
    }
  ]
}
